pylambda/__init__.py
pylambda/__init__.pyc
pylambda/deploy.py
pylambda/deploy.pyc
pylambda/lambda_local.py
pylambda/lambda_local.pyc
pylambda-0.2.1.dist-info/DESCRIPTION.rst
pylambda-0.2.1.dist-info/METADATA
pylambda-0.2.1.dist-info/RECORD
pylambda-0.2.1.dist-info/WHEEL
pylambda-0.2.1.dist-info/entry_points.txt
pylambda-0.2.1.dist-info/metadata.json
pylambda-0.2.1.dist-info/top_level.txt
test/__init__.py
test/__init__.pyc
test/fake_lambda.py
test/test_aws_lambda.py
test/test_deploy.py
test/__pycache__/test_aws_lambda.cpython-27-PYTEST.pyc
test/__pycache__/test_deploy.cpython-27-PYTEST.pyc
