Metadata-Version: 1.0
Name: pylambda
Version: 0.2.1
Summary: Run your local python AWS Lambda locally and deploy to S3.
Home-page: https://github.com/PitchBook/pylambda
Author: Nicholas Ames
Author-email: UNKNOWN
License: MIT
Keywords: aws lambda s3
Platform: UNKNOWN
